<tfg>
    <title>TFG hírek</title>
    <link><![CDATA[https://github.com/TFGitp/tfg-kliens]]></link>
    <item>
        <title>MesterMC</title>
        <link><![CDATA[https://tfg.hu]]></link>
        <intro>MesterMC helyett egy modern kliens</intro>
        <content>Jelenleg a kliens azért néz ki úgy, mint a MesterMC, mert ez egy régi projektem volt arra, és néhány nap alatt kellett elkészülnie, hogy a TFG mod/világot le tudja tölteni. Hamarosan egy modernebb kinézetet kap!</content>
        <img><![CDATA[https://8219084876.cbaul-cdnwnd.com/63d20e91c760280e67da7e7eb69b8fef/system_preview_detail_200000000-05659065e5-public/MesterMc.png]]></img>
    </item>
</tfg>
